{
  "datetime": "2026-07-07 02:00:58 UTC",
  "cid": "41295663",
  "name": "Boa Hancock P [P-066]",
  "code": "P-066",
  "rarity": "C",
  "price": "¥33,600",
  "price_int": 33600,
  "prev_price": "¥33,600",
  "image_url": "https://cdn.snkrdunk.com/apparel_used_listings/6fa7f9e9-855f-48be-9aac-0d06d26f43ab/7369990.jpeg?size=m",
  "history": [
    {
      "t": 1782577462,
      "p": 48000
    },
    {
      "t": 1782580591,
      "p": 34900
    },
    {
      "t": 1782628677,
      "p": 34500
    },
    {
      "t": 1782631788,
      "p": 34900
    },
    {
      "t": 1782646792,
      "p": 34800
    },
    {
      "t": 1782904599,
      "p": 34500
    },
    {
      "t": 1782916683,
      "p": 34000
    },
    {
      "t": 1782918307,
      "p": 33900
    },
    {
      "t": 1783000727,
      "p": 34000
    },
    {
      "t": 1783357866,
      "p": 33600
    }
  ],
  "product_url": "https://snkrdunk.com/search?keywords=Boa+Hancock+P+%5BP-066%5D&sort=price_low&itemConditions=psa_10&isSaleOnly=true&page=1",
  "status": "ok"
}