{
  "datetime": "2026-07-01 22:51:22 UTC",
  "cid": "42173984",
  "name": "Luffy [OP05-119] L03",
  "code": "CUSTOM",
  "rarity": "C",
  "price": "¥47,800",
  "price_int": 47800,
  "prev_price": "¥47,800",
  "image_url": "https://cdn.snkrdunk.com/apparel_used_listings/325f6075-6707-47fa-9007-3c206d5ba9e0/7577792.jpeg?size=m",
  "history": [
    {
      "t": 1782631947,
      "p": 49000
    },
    {
      "t": 1782659247,
      "p": 48900
    },
    {
      "t": 1782733506,
      "p": 48500
    },
    {
      "t": 1782829620,
      "p": 48000
    },
    {
      "t": 1782940158,
      "p": 47800
    }
  ],
  "product_url": "https://snkrdunk.com/search?keywords=Luffy+SEC-P+OP05-119&sort=price_low&itemConditions=psa_10&isSaleOnly=true&page=1",
  "status": "ok"
}