{
  "datetime": "2026-07-24 12:30:54 UTC",
  "cid": "8c8ef17d",
  "name": "Zoro R-P [PRB02-006]",
  "code": "CUSTOM",
  "rarity": "C",
  "price": "¥39,500",
  "price_int": 39500,
  "prev_price": "¥39,500",
  "image_url": "https://cdn.snkrdunk.com/apparel_used_listings/0178421c-802c-4a3c-9e8d-990c6c240876/4578138.jpeg?size=m",
  "history": [
    {
      "t": 1782712851,
      "p": 37999
    },
    {
      "t": 1783203012,
      "p": 36999
    },
    {
      "t": 1783303683,
      "p": 37999
    },
    {
      "t": 1783647116,
      "p": 36999
    },
    {
      "t": 1784135818,
      "p": 37999
    },
    {
      "t": 1784854924,
      "p": 39500
    }
  ],
  "product_url": "https://snkrdunk.com/search?keywords=R-P+%5BPRB02-006%5D&sort=price_low&itemConditions=psa_10&isSaleOnly=true&page=1",
  "status": "ok"
}